readability_cn/__init__.py
readability_cn/readability.py
readability_cn/data/CorpusWordlist.csv
readability_cn/data/character_frequency.csv
readability_cn/data/ci_jia.txt
readability_cn/data/common-zi.txt
readability_cn/data/filtered_computer.vocab
readability_cn/data/hanzi_jia.txt
readability_cn/data/hsk3_vocabulary.txt
readability_cn/data/zi-dataset.tsv
readability_cn-0.1.4.dist-info/LICENSE
readability_cn-0.1.4.dist-info/METADATA
readability_cn-0.1.4.dist-info/WHEEL
readability_cn-0.1.4.dist-info/entry_points.txt
readability_cn-0.1.4.dist-info/top_level.txt
readability_cn-0.1.4.dist-info/RECORD
