Metadata-Version: 2.1
Name: readability_cn
Version: 0.1.4
Summary: 计算中文文本可读性指标
Home-page: http://github.com/chenryn/python-readability-cn
Author: chenryn
Author-email: rao.chenlin@gmail.com
Classifier: Programming Language :: Python :: 3
Classifier: Programming Language :: Python :: 3.6
Classifier: Programming Language :: Python :: 3.7
Classifier: Programming Language :: Python :: 3.8
Classifier: Programming Language :: Python :: 3.9
Classifier: License :: OSI Approved :: MIT License
Classifier: Operating System :: OS Independent
Classifier: Intended Audience :: Developers
Classifier: Intended Audience :: Science/Research
Classifier: Topic :: Text Processing :: Linguistic
Classifier: Development Status :: 3 - Alpha
Requires-Python: >=3.6
License-File: LICENSE
Requires-Dist: numpy
Requires-Dist: ltp
Requires-Dist: torch
